bivapp/__init__.py
bivapp/plots.py
bivapp/sampledata.py
bivapp/sampledata/NO2_2023.csv
bivapp/sampledata/climate-hourly.csv
bivapp/sampledata/openair_test_data.csv
bivapp-0.1.1.dist-info/METADATA
bivapp-0.1.1.dist-info/WHEEL
bivapp-0.1.1.dist-info/licenses/LICENSE
bivapp-0.1.1.dist-info/RECORD
