Metadata-Version: 2.4
Name: bivapp
Version: 0.1.1
Summary: Bivariate polar plots in Python
Author-email: "Taylor D. Edwards" <td.edwards@yahoo.com>
License-File: LICENSE
Classifier: Operating System :: OS Independent
Classifier: Programming Language :: Python :: 3
Requires-Python: >=3.11.8
Requires-Dist: cmcrameri>=1.8
Requires-Dist: matplotlib>=3.10.1
Requires-Dist: numpy==2.2.5
Requires-Dist: pandas==2.2.3
Requires-Dist: pygam>=0.8.0
Requires-Dist: scipy==1.15.2
Requires-Dist: shapely>=2.1.0
